yaml_to_langgraph/__init__.py
yaml_to_langgraph/__main__.py
yaml_to_langgraph/cli.py
yaml_to_langgraph/code_generator.py
yaml_to_langgraph/converter.py
yaml_to_langgraph/graph_visualizer.py
yaml_to_langgraph/schema_validator.py
yaml_to_langgraph/yaml_parser.py
yaml_to_langgraph-1.0.3.dist-info/METADATA
yaml_to_langgraph-1.0.3.dist-info/WHEEL
yaml_to_langgraph-1.0.3.dist-info/entry_points.txt
yaml_to_langgraph-1.0.3.dist-info/licenses/LICENSE
yaml_to_langgraph-1.0.3.dist-info/RECORD
